<annotation>
    <filename>010_005.png</filename>
    <size>
        <width>1653</width>
        <height>2339</height>
        <depth>3</depth>
    </size>
    <segmented>0</segmented>
    <object>
        <name>inlinemf</name>
        <pose>Unspecified</pose>
        <truncated>0</truncated>
        <occluded>0</occluded>
        <difficult>0</difficult>
        <bndbox>
            <xmin>1386</xmin>
            <ymin>433</ymin>
            <xmax>1423</xmax>
            <ymax>465</ymax>
        </bndbox>
    </object>
    <object>
        <name>inlinemf</name>
        <pose>Unspecified</pose>
        <truncated>0</truncated>
        <occluded>0</occluded>
        <difficult>0</difficult>
        <bndbox>
            <xmin>476</xmin>
            <ymin>942</ymin>
            <xmax>503</xmax>
            <ymax>971</ymax>
        </bndbox>
    </object>
    <object>
        <name>inlinemf</name>
        <pose>Unspecified</pose>
        <truncated>0</truncated>
        <occluded>0</occluded>
        <difficult>0</difficult>
        <bndbox>
            <xmin>1306</xmin>
            <ymin>1573</ymin>
            <xmax>1394</xmax>
            <ymax>1608</ymax>
        </bndbox>
    </object>
    <object>
        <name>inlinemf</name>
        <pose>Unspecified</pose>
        <truncated>0</truncated>
        <occluded>0</occluded>
        <difficult>0</difficult>
        <bndbox>
            <xmin>999</xmin>
            <ymin>1579</ymin>
            <xmax>1030</xmax>
            <ymax>1604</ymax>
        </bndbox>
    </object>
    <object>
        <name>inlinemf</name>
        <pose>Unspecified</pose>
        <truncated>0</truncated>
        <occluded>0</occluded>
        <difficult>0</difficult>
        <bndbox>
            <xmin>274</xmin>
            <ymin>1853</ymin>
            <xmax>309</xmax>
            <ymax>1876</ymax>
        </bndbox>
    </object>
    <object>
        <name>inlinemf</name>
        <pose>Unspecified</pose>
        <truncated>0</truncated>
        <occluded>0</occluded>
        <difficult>0</difficult>
        <bndbox>
            <xmin>1331</xmin>
            <ymin>1280</ymin>
            <xmax>1368</xmax>
            <ymax>1312</ymax>
        </bndbox>
    </object>
    <object>
        <name>inlinemf</name>
        <pose>Unspecified</pose>
        <truncated>0</truncated>
        <occluded>0</occluded>
        <difficult>0</difficult>
        <bndbox>
            <xmin>908</xmin>
            <ymin>1405</ymin>
            <xmax>945</xmax>
            <ymax>1437</ymax>
        </bndbox>
    </object>
    <object>
        <name>inlinemf</name>
        <pose>Unspecified</pose>
        <truncated>0</truncated>
        <occluded>0</occluded>
        <difficult>0</difficult>
        <bndbox>
            <xmin>509</xmin>
            <ymin>1750</ymin>
            <xmax>529</xmax>
            <ymax>1778</ymax>
        </bndbox>
    </object>
    <object>
        <name>inlinemf</name>
        <pose>Unspecified</pose>
        <truncated>0</truncated>
        <occluded>0</occluded>
        <difficult>0</difficult>
        <bndbox>
            <xmin>1129</xmin>
            <ymin>1280</ymin>
            <xmax>1166</xmax>
            <ymax>1312</ymax>
        </bndbox>
    </object>
    <object>
        <name>inlinemf</name>
        <pose>Unspecified</pose>
        <truncated>0</truncated>
        <occluded>0</occluded>
        <difficult>0</difficult>
        <bndbox>
            <xmin>770</xmin>
            <ymin>1950</ymin>
            <xmax>805</xmax>
            <ymax>1973</ymax>
        </bndbox>
    </object>
    <object>
        <name>inlinemf</name>
        <pose>Unspecified</pose>
        <truncated>0</truncated>
        <occluded>0</occluded>
        <difficult>0</difficult>
        <bndbox>
            <xmin>676</xmin>
            <ymin>1784</ymin>
            <xmax>696</xmax>
            <ymax>1812</ymax>
        </bndbox>
    </object>
    <object>
        <name>inlinemf</name>
        <pose>Unspecified</pose>
        <truncated>0</truncated>
        <occluded>0</occluded>
        <difficult>0</difficult>
        <bndbox>
            <xmin>1082</xmin>
            <ymin>729</ymin>
            <xmax>1119</xmax>
            <ymax>761</ymax>
        </bndbox>
    </object>
    <object>
        <name>inlinemf</name>
        <pose>Unspecified</pose>
        <truncated>0</truncated>
        <occluded>0</occluded>
        <difficult>0</difficult>
        <bndbox>
            <xmin>570</xmin>
            <ymin>1721</ymin>
            <xmax>646</xmax>
            <ymax>1747</ymax>
        </bndbox>
    </object>
    <object>
        <name>inlinemf</name>
        <pose>Unspecified</pose>
        <truncated>0</truncated>
        <occluded>0</occluded>
        <difficult>0</difficult>
        <bndbox>
            <xmin>478</xmin>
            <ymin>900</ymin>
            <xmax>505</xmax>
            <ymax>929</ymax>
        </bndbox>
    </object>
    <object>
        <name>inlinemf</name>
        <pose>Unspecified</pose>
        <truncated>0</truncated>
        <occluded>0</occluded>
        <difficult>0</difficult>
        <bndbox>
            <xmin>279</xmin>
            <ymin>1689</ymin>
            <xmax>331</xmax>
            <ymax>1714</ymax>
        </bndbox>
    </object>
    <object>
        <name>inlinemf</name>
        <pose>Unspecified</pose>
        <truncated>0</truncated>
        <occluded>0</occluded>
        <difficult>0</difficult>
        <bndbox>
            <xmin>783</xmin>
            <ymin>1849</ymin>
            <xmax>803</xmax>
            <ymax>1877</ymax>
        </bndbox>
    </object>
    <object>
        <name>inlinemf</name>
        <pose>Unspecified</pose>
        <truncated>0</truncated>
        <occluded>0</occluded>
        <difficult>0</difficult>
        <bndbox>
            <xmin>456</xmin>
            <ymin>262</ymin>
            <xmax>502</xmax>
            <ymax>294</ymax>
        </bndbox>
    </object>
    <object>
        <name>inlinemf</name>
        <pose>Unspecified</pose>
        <truncated>0</truncated>
        <occluded>0</occluded>
        <difficult>0</difficult>
        <bndbox>
            <xmin>753</xmin>
            <ymin>1721</ymin>
            <xmax>773</xmax>
            <ymax>1747</ymax>
        </bndbox>
    </object>
    <object>
        <name>inlinemf</name>
        <pose>Unspecified</pose>
        <truncated>0</truncated>
        <occluded>0</occluded>
        <difficult>0</difficult>
        <bndbox>
            <xmin>891</xmin>
            <ymin>519</ymin>
            <xmax>928</xmax>
            <ymax>551</ymax>
        </bndbox>
    </object>
    <object>
        <name>inlinemf</name>
        <pose>Unspecified</pose>
        <truncated>0</truncated>
        <occluded>0</occluded>
        <difficult>0</difficult>
        <bndbox>
            <xmin>279</xmin>
            <ymin>1881</ymin>
            <xmax>303</xmax>
            <ymax>1906</ymax>
        </bndbox>
    </object>
    <object>
        <name>inlinemf</name>
        <pose>Unspecified</pose>
        <truncated>0</truncated>
        <occluded>0</occluded>
        <difficult>0</difficult>
        <bndbox>
            <xmin>977</xmin>
            <ymin>562</ymin>
            <xmax>1014</xmax>
            <ymax>594</ymax>
        </bndbox>
    </object>
    <object>
        <name>inlinemf</name>
        <pose>Unspecified</pose>
        <truncated>0</truncated>
        <occluded>0</occluded>
        <difficult>0</difficult>
        <bndbox>
            <xmin>910</xmin>
            <ymin>1572</ymin>
            <xmax>947</xmax>
            <ymax>1604</ymax>
        </bndbox>
    </object>
    <object>
        <name>inlinemf</name>
        <pose>Unspecified</pose>
        <truncated>0</truncated>
        <occluded>0</occluded>
        <difficult>0</difficult>
        <bndbox>
            <xmin>853</xmin>
            <ymin>1278</ymin>
            <xmax>877</xmax>
            <ymax>1305</ymax>
        </bndbox>
    </object>
    <object>
        <name>inlinemf</name>
        <pose>Unspecified</pose>
        <truncated>0</truncated>
        <occluded>0</occluded>
        <difficult>0</difficult>
        <bndbox>
            <xmin>1135</xmin>
            <ymin>898</ymin>
            <xmax>1172</xmax>
            <ymax>930</ymax>
        </bndbox>
    </object>
    <object>
        <name>inlinemf</name>
        <pose>Unspecified</pose>
        <truncated>0</truncated>
        <occluded>0</occluded>
        <difficult>0</difficult>
        <bndbox>
            <xmin>1390</xmin>
            <ymin>308</ymin>
            <xmax>1427</xmax>
            <ymax>340</ymax>
        </bndbox>
    </object>
    <object>
        <name>inlinemf</name>
        <pose>Unspecified</pose>
        <truncated>0</truncated>
        <occluded>0</occluded>
        <difficult>0</difficult>
        <bndbox>
            <xmin>142</xmin>
            <ymin>1247</ymin>
            <xmax>169</xmax>
            <ymax>1276</ymax>
        </bndbox>
    </object>
    <object>
        <name>inlinemf</name>
        <pose>Unspecified</pose>
        <truncated>0</truncated>
        <occluded>0</occluded>
        <difficult>0</difficult>
        <bndbox>
            <xmin>1399</xmin>
            <ymin>561</ymin>
            <xmax>1500</xmax>
            <ymax>593</ymax>
        </bndbox>
    </object>
    <object>
        <name>inlinemf</name>
        <pose>Unspecified</pose>
        <truncated>0</truncated>
        <occluded>0</occluded>
        <difficult>0</difficult>
        <bndbox>
            <xmin>1011</xmin>
            <ymin>1361</ymin>
            <xmax>1048</xmax>
            <ymax>1393</ymax>
        </bndbox>
    </object>
    <object>
        <name>inlinemf</name>
        <pose>Unspecified</pose>
        <truncated>0</truncated>
        <occluded>0</occluded>
        <difficult>0</difficult>
        <bndbox>
            <xmin>428</xmin>
            <ymin>305</ymin>
            <xmax>474</xmax>
            <ymax>337</ymax>
        </bndbox>
    </object>
    <object>
        <name>inlinemf</name>
        <pose>Unspecified</pose>
        <truncated>0</truncated>
        <occluded>0</occluded>
        <difficult>0</difficult>
        <bndbox>
            <xmin>1350</xmin>
            <ymin>1237</ymin>
            <xmax>1400</xmax>
            <ymax>1267</ymax>
        </bndbox>
    </object>
    <object>
        <name>inlinemf</name>
        <pose>Unspecified</pose>
        <truncated>0</truncated>
        <occluded>0</occluded>
        <difficult>0</difficult>
        <bndbox>
            <xmin>537</xmin>
            <ymin>1695</ymin>
            <xmax>572</xmax>
            <ymax>1718</ymax>
        </bndbox>
    </object>
    <object>
        <name>inlinemf</name>
        <pose>Unspecified</pose>
        <truncated>0</truncated>
        <occluded>0</occluded>
        <difficult>0</difficult>
        <bndbox>
            <xmin>287</xmin>
            <ymin>941</ymin>
            <xmax>320</xmax>
            <ymax>971</ymax>
        </bndbox>
    </object>
    <object>
        <name>inlinemf</name>
        <pose>Unspecified</pose>
        <truncated>0</truncated>
        <occluded>0</occluded>
        <difficult>0</difficult>
        <bndbox>
            <xmin>1402</xmin>
            <ymin>732</ymin>
            <xmax>1426</xmax>
            <ymax>759</ymax>
        </bndbox>
    </object>
    <object>
        <name>inlinemf</name>
        <pose>Unspecified</pose>
        <truncated>0</truncated>
        <occluded>0</occluded>
        <difficult>0</difficult>
        <bndbox>
            <xmin>565</xmin>
            <ymin>391</ymin>
            <xmax>676</xmax>
            <ymax>424</ymax>
        </bndbox>
    </object>
    <object>
        <name>inlinemf</name>
        <pose>Unspecified</pose>
        <truncated>0</truncated>
        <occluded>0</occluded>
        <difficult>0</difficult>
        <bndbox>
            <xmin>1016</xmin>
            <ymin>308</ymin>
            <xmax>1053</xmax>
            <ymax>340</ymax>
        </bndbox>
    </object>
    <object>
        <name>inlinemf</name>
        <pose>Unspecified</pose>
        <truncated>0</truncated>
        <occluded>0</occluded>
        <difficult>0</difficult>
        <bndbox>
            <xmin>896</xmin>
            <ymin>434</ymin>
            <xmax>942</xmax>
            <ymax>466</ymax>
        </bndbox>
    </object>
    <object>
        <name>inlinemf</name>
        <pose>Unspecified</pose>
        <truncated>0</truncated>
        <occluded>0</occluded>
        <difficult>0</difficult>
        <bndbox>
            <xmin>1132</xmin>
            <ymin>563</ymin>
            <xmax>1156</xmax>
            <ymax>590</ymax>
        </bndbox>
    </object>
    <object>
        <name>inlinemf</name>
        <pose>Unspecified</pose>
        <truncated>0</truncated>
        <occluded>0</occluded>
        <difficult>0</difficult>
        <bndbox>
            <xmin>637</xmin>
            <ymin>1247</ymin>
            <xmax>789</xmax>
            <ymax>1282</ymax>
        </bndbox>
    </object>
    <object>
        <name>inlinemf</name>
        <pose>Unspecified</pose>
        <truncated>0</truncated>
        <occluded>0</occluded>
        <difficult>0</difficult>
        <bndbox>
            <xmin>1142</xmin>
            <ymin>436</ymin>
            <xmax>1166</xmax>
            <ymax>463</ymax>
        </bndbox>
    </object>
    <object>
        <name>inlinemf</name>
        <pose>Unspecified</pose>
        <truncated>0</truncated>
        <occluded>0</occluded>
        <difficult>0</difficult>
        <bndbox>
            <xmin>1463</xmin>
            <ymin>1490</ymin>
            <xmax>1513</xmax>
            <ymax>1520</ymax>
        </bndbox>
    </object>
    <object>
        <name>inlinemf</name>
        <pose>Unspecified</pose>
        <truncated>0</truncated>
        <occluded>0</occluded>
        <difficult>0</difficult>
        <bndbox>
            <xmin>1076</xmin>
            <ymin>1321</ymin>
            <xmax>1100</xmax>
            <ymax>1348</ymax>
        </bndbox>
    </object>
</annotation>