<annotation>
    <filename>038_004.png</filename>
    <size>
        <width>1654</width>
        <height>2339</height>
        <depth>3</depth>
    </size>
    <segmented>0</segmented>
    <object>
        <name>inlinemf</name>
        <pose>Unspecified</pose>
        <truncated>0</truncated>
        <occluded>0</occluded>
        <difficult>0</difficult>
        <bndbox>
            <xmin>1107</xmin>
            <ymin>606</ymin>
            <xmax>1185</xmax>
            <ymax>646</ymax>
        </bndbox>
    </object>
    <object>
        <name>inlinemf</name>
        <pose>Unspecified</pose>
        <truncated>0</truncated>
        <occluded>0</occluded>
        <difficult>0</difficult>
        <bndbox>
            <xmin>170</xmin>
            <ymin>1785</ymin>
            <xmax>244</xmax>
            <ymax>1823</ymax>
        </bndbox>
    </object>
    <object>
        <name>inlinemf</name>
        <pose>Unspecified</pose>
        <truncated>0</truncated>
        <occluded>0</occluded>
        <difficult>0</difficult>
        <bndbox>
            <xmin>1077</xmin>
            <ymin>1763</ymin>
            <xmax>1131</xmax>
            <ymax>1790</ymax>
        </bndbox>
    </object>
    <object>
        <name>inlinemf</name>
        <pose>Unspecified</pose>
        <truncated>0</truncated>
        <occluded>0</occluded>
        <difficult>0</difficult>
        <bndbox>
            <xmin>195</xmin>
            <ymin>1750</ymin>
            <xmax>576</xmax>
            <ymax>1784</ymax>
        </bndbox>
    </object>
    <object>
        <name>inlinemf</name>
        <pose>Unspecified</pose>
        <truncated>0</truncated>
        <occluded>0</occluded>
        <difficult>0</difficult>
        <bndbox>
            <xmin>901</xmin>
            <ymin>2080</ymin>
            <xmax>966</xmax>
            <ymax>2114</ymax>
        </bndbox>
    </object>
    <object>
        <name>inlinemf</name>
        <pose>Unspecified</pose>
        <truncated>0</truncated>
        <occluded>0</occluded>
        <difficult>0</difficult>
        <bndbox>
            <xmin>924</xmin>
            <ymin>1519</ymin>
            <xmax>950</xmax>
            <ymax>1543</ymax>
        </bndbox>
    </object>
    <object>
        <name>inlinemf</name>
        <pose>Unspecified</pose>
        <truncated>0</truncated>
        <occluded>0</occluded>
        <difficult>0</difficult>
        <bndbox>
            <xmin>249</xmin>
            <ymin>1945</ymin>
            <xmax>283</xmax>
            <ymax>1982</ymax>
        </bndbox>
    </object>
    <object>
        <name>inlinemf</name>
        <pose>Unspecified</pose>
        <truncated>0</truncated>
        <occluded>0</occluded>
        <difficult>0</difficult>
        <bndbox>
            <xmin>841</xmin>
            <ymin>1278</ymin>
            <xmax>871</xmax>
            <ymax>1308</ymax>
        </bndbox>
    </object>
    <object>
        <name>inlinemf</name>
        <pose>Unspecified</pose>
        <truncated>0</truncated>
        <occluded>0</occluded>
        <difficult>0</difficult>
        <bndbox>
            <xmin>1027</xmin>
            <ymin>1559</ymin>
            <xmax>1048</xmax>
            <ymax>1582</ymax>
        </bndbox>
    </object>
    <object>
        <name>inlinemf</name>
        <pose>Unspecified</pose>
        <truncated>0</truncated>
        <occluded>0</occluded>
        <difficult>0</difficult>
        <bndbox>
            <xmin>843</xmin>
            <ymin>1203</ymin>
            <xmax>866</xmax>
            <ymax>1227</ymax>
        </bndbox>
    </object>
    <object>
        <name>inlinemf</name>
        <pose>Unspecified</pose>
        <truncated>0</truncated>
        <occluded>0</occluded>
        <difficult>0</difficult>
        <bndbox>
            <xmin>1281</xmin>
            <ymin>1163</ymin>
            <xmax>1304</xmax>
            <ymax>1187</ymax>
        </bndbox>
    </object>
    <object>
        <name>inlinemf</name>
        <pose>Unspecified</pose>
        <truncated>0</truncated>
        <occluded>0</occluded>
        <difficult>0</difficult>
        <bndbox>
            <xmin>873</xmin>
            <ymin>1801</ymin>
            <xmax>962</xmax>
            <ymax>1831</ymax>
        </bndbox>
    </object>
    <object>
        <name>inlinemf</name>
        <pose>Unspecified</pose>
        <truncated>0</truncated>
        <occluded>0</occluded>
        <difficult>0</difficult>
        <bndbox>
            <xmin>751</xmin>
            <ymin>1905</ymin>
            <xmax>785</xmax>
            <ymax>1942</ymax>
        </bndbox>
    </object>
    <object>
        <name>inlinemf</name>
        <pose>Unspecified</pose>
        <truncated>0</truncated>
        <occluded>0</occluded>
        <difficult>0</difficult>
        <bndbox>
            <xmin>1312</xmin>
            <ymin>1760</ymin>
            <xmax>1383</xmax>
            <ymax>1792</ymax>
        </bndbox>
    </object>
    <object>
        <name>inlinemf</name>
        <pose>Unspecified</pose>
        <truncated>0</truncated>
        <occluded>0</occluded>
        <difficult>0</difficult>
        <bndbox>
            <xmin>1463</xmin>
            <ymin>2008</ymin>
            <xmax>1488</xmax>
            <ymax>2031</ymax>
        </bndbox>
    </object>
    <object>
        <name>inlinemf</name>
        <pose>Unspecified</pose>
        <truncated>0</truncated>
        <occluded>0</occluded>
        <difficult>0</difficult>
        <bndbox>
            <xmin>542</xmin>
            <ymin>2101</ymin>
            <xmax>577</xmax>
            <ymax>2139</ymax>
        </bndbox>
    </object>
    <object>
        <name>inlinemf</name>
        <pose>Unspecified</pose>
        <truncated>0</truncated>
        <occluded>0</occluded>
        <difficult>0</difficult>
        <bndbox>
            <xmin>873</xmin>
            <ymin>605</ymin>
            <xmax>951</xmax>
            <ymax>645</ymax>
        </bndbox>
    </object>
    <object>
        <name>inlinemf</name>
        <pose>Unspecified</pose>
        <truncated>0</truncated>
        <occluded>0</occluded>
        <difficult>0</difficult>
        <bndbox>
            <xmin>1163</xmin>
            <ymin>1197</ymin>
            <xmax>1256</xmax>
            <ymax>1231</ymax>
        </bndbox>
    </object>
</annotation>