<annotation>
    <filename>100_004.png</filename>
    <size>
        <width>1654</width>
        <height>2339</height>
        <depth>3</depth>
    </size>
    <segmented>0</segmented>
    <object>
        <name>inlinemf</name>
        <pose>Unspecified</pose>
        <truncated>0</truncated>
        <occluded>0</occluded>
        <difficult>0</difficult>
        <bndbox>
            <xmin>482</xmin>
            <ymin>637</ymin>
            <xmax>533</xmax>
            <ymax>671</ymax>
        </bndbox>
    </object>
    <object>
        <name>inlinemf</name>
        <pose>Unspecified</pose>
        <truncated>0</truncated>
        <occluded>0</occluded>
        <difficult>0</difficult>
        <bndbox>
            <xmin>1381</xmin>
            <ymin>1836</ymin>
            <xmax>1470</xmax>
            <ymax>1870</ymax>
        </bndbox>
    </object>
    <object>
        <name>inlinemf</name>
        <pose>Unspecified</pose>
        <truncated>0</truncated>
        <occluded>0</occluded>
        <difficult>0</difficult>
        <bndbox>
            <xmin>248</xmin>
            <ymin>2025</ymin>
            <xmax>268</xmax>
            <ymax>2052</ymax>
        </bndbox>
    </object>
    <object>
        <name>inlinemf</name>
        <pose>Unspecified</pose>
        <truncated>0</truncated>
        <occluded>0</occluded>
        <difficult>0</difficult>
        <bndbox>
            <xmin>1121</xmin>
            <ymin>655</ymin>
            <xmax>1140</xmax>
            <ymax>676</ymax>
        </bndbox>
    </object>
    <object>
        <name>inlinemf</name>
        <pose>Unspecified</pose>
        <truncated>0</truncated>
        <occluded>0</occluded>
        <difficult>0</difficult>
        <bndbox>
            <xmin>1112</xmin>
            <ymin>1956</ymin>
            <xmax>1194</xmax>
            <ymax>1989</ymax>
        </bndbox>
    </object>
    <object>
        <name>inlinemf</name>
        <pose>Unspecified</pose>
        <truncated>0</truncated>
        <occluded>0</occluded>
        <difficult>0</difficult>
        <bndbox>
            <xmin>1089</xmin>
            <ymin>571</ymin>
            <xmax>1159</xmax>
            <ymax>602</ymax>
        </bndbox>
    </object>
    <object>
        <name>inlinemf</name>
        <pose>Unspecified</pose>
        <truncated>0</truncated>
        <occluded>0</occluded>
        <difficult>0</difficult>
        <bndbox>
            <xmin>1118</xmin>
            <ymin>1724</ymin>
            <xmax>1160</xmax>
            <ymax>1753</ymax>
        </bndbox>
    </object>
    <object>
        <name>inlinemf</name>
        <pose>Unspecified</pose>
        <truncated>0</truncated>
        <occluded>0</occluded>
        <difficult>0</difficult>
        <bndbox>
            <xmin>412</xmin>
            <ymin>638</ymin>
            <xmax>465</xmax>
            <ymax>671</ymax>
        </bndbox>
    </object>
    <object>
        <name>inlinemf</name>
        <pose>Unspecified</pose>
        <truncated>0</truncated>
        <occluded>0</occluded>
        <difficult>0</difficult>
        <bndbox>
            <xmin>337</xmin>
            <ymin>873</ymin>
            <xmax>402</xmax>
            <ymax>909</ymax>
        </bndbox>
    </object>
    <object>
        <name>inlinemf</name>
        <pose>Unspecified</pose>
        <truncated>0</truncated>
        <occluded>0</occluded>
        <difficult>0</difficult>
        <bndbox>
            <xmin>573</xmin>
            <ymin>1708</ymin>
            <xmax>678</xmax>
            <ymax>1739</ymax>
        </bndbox>
    </object>
    <object>
        <name>inlinemf</name>
        <pose>Unspecified</pose>
        <truncated>0</truncated>
        <occluded>0</occluded>
        <difficult>0</difficult>
        <bndbox>
            <xmin>1208</xmin>
            <ymin>572</ymin>
            <xmax>1276</xmax>
            <ymax>603</ymax>
        </bndbox>
    </object>
    <object>
        <name>inlinemf</name>
        <pose>Unspecified</pose>
        <truncated>0</truncated>
        <occluded>0</occluded>
        <difficult>0</difficult>
        <bndbox>
            <xmin>1358</xmin>
            <ymin>1917</ymin>
            <xmax>1438</xmax>
            <ymax>1950</ymax>
        </bndbox>
    </object>
    <object>
        <name>inlinemf</name>
        <pose>Unspecified</pose>
        <truncated>0</truncated>
        <occluded>0</occluded>
        <difficult>0</difficult>
        <bndbox>
            <xmin>209</xmin>
            <ymin>915</ymin>
            <xmax>252</xmax>
            <ymax>946</ymax>
        </bndbox>
    </object>
    <object>
        <name>displaymf</name>
        <pose>Unspecified</pose>
        <truncated>0</truncated>
        <occluded>0</occluded>
        <difficult>0</difficult>
        <bndbox>
            <xmin>324</xmin>
            <ymin>1959</ymin>
            <xmax>559</xmax>
            <ymax>1998</ymax>
        </bndbox>
    </object>
    <object>
        <name>displaymf</name>
        <pose>Unspecified</pose>
        <truncated>0</truncated>
        <occluded>0</occluded>
        <difficult>0</difficult>
        <bndbox>
            <xmin>265</xmin>
            <ymin>732</ymin>
            <xmax>618</xmax>
            <ymax>773</ymax>
        </bndbox>
    </object>
    <object>
        <name>inlinemf</name>
        <pose>Unspecified</pose>
        <truncated>0</truncated>
        <occluded>0</occluded>
        <difficult>0</difficult>
        <bndbox>
            <xmin>155</xmin>
            <ymin>1506</ymin>
            <xmax>202</xmax>
            <ymax>1540</ymax>
        </bndbox>
    </object>
    <object>
        <name>inlinemf</name>
        <pose>Unspecified</pose>
        <truncated>0</truncated>
        <occluded>0</occluded>
        <difficult>0</difficult>
        <bndbox>
            <xmin>657</xmin>
            <ymin>954</ymin>
            <xmax>700</xmax>
            <ymax>985</ymax>
        </bndbox>
    </object>
    <object>
        <name>inlinemf</name>
        <pose>Unspecified</pose>
        <truncated>0</truncated>
        <occluded>0</occluded>
        <difficult>0</difficult>
        <bndbox>
            <xmin>879</xmin>
            <ymin>1876</ymin>
            <xmax>967</xmax>
            <ymax>1909</ymax>
        </bndbox>
    </object>
    <object>
        <name>inlinemf</name>
        <pose>Unspecified</pose>
        <truncated>0</truncated>
        <occluded>0</occluded>
        <difficult>0</difficult>
        <bndbox>
            <xmin>456</xmin>
            <ymin>1469</ymin>
            <xmax>505</xmax>
            <ymax>1499</ymax>
        </bndbox>
    </object>
</annotation>