<annotation>
    <filename>155_005.png</filename>
    <size>
        <width>1654</width>
        <height>2339</height>
        <depth>3</depth>
    </size>
    <segmented>0</segmented>
    <object>
        <name>inlinemf</name>
        <pose>Unspecified</pose>
        <truncated>0</truncated>
        <occluded>0</occluded>
        <difficult>0</difficult>
        <bndbox>
            <xmin>145</xmin>
            <ymin>1862</ymin>
            <xmax>340</xmax>
            <ymax>1895</ymax>
        </bndbox>
    </object>
    <object>
        <name>inlinemf</name>
        <pose>Unspecified</pose>
        <truncated>0</truncated>
        <occluded>0</occluded>
        <difficult>0</difficult>
        <bndbox>
            <xmin>1429</xmin>
            <ymin>2155</ymin>
            <xmax>1476</xmax>
            <ymax>2183</ymax>
        </bndbox>
    </object>
    <object>
        <name>inlinemf</name>
        <pose>Unspecified</pose>
        <truncated>0</truncated>
        <occluded>0</occluded>
        <difficult>0</difficult>
        <bndbox>
            <xmin>528</xmin>
            <ymin>1615</ymin>
            <xmax>551</xmax>
            <ymax>1641</ymax>
        </bndbox>
    </object>
    <object>
        <name>inlinemf</name>
        <pose>Unspecified</pose>
        <truncated>0</truncated>
        <occluded>0</occluded>
        <difficult>0</difficult>
        <bndbox>
            <xmin>652</xmin>
            <ymin>1688</ymin>
            <xmax>668</xmax>
            <ymax>1714</ymax>
        </bndbox>
    </object>
    <object>
        <name>inlinemf</name>
        <pose>Unspecified</pose>
        <truncated>0</truncated>
        <occluded>0</occluded>
        <difficult>0</difficult>
        <bndbox>
            <xmin>1157</xmin>
            <ymin>1721</ymin>
            <xmax>1232</xmax>
            <ymax>1752</ymax>
        </bndbox>
    </object>
    <object>
        <name>inlinemf</name>
        <pose>Unspecified</pose>
        <truncated>0</truncated>
        <occluded>0</occluded>
        <difficult>0</difficult>
        <bndbox>
            <xmin>456</xmin>
            <ymin>1936</ymin>
            <xmax>489</xmax>
            <ymax>1962</ymax>
        </bndbox>
    </object>
    <object>
        <name>inlinemf</name>
        <pose>Unspecified</pose>
        <truncated>0</truncated>
        <occluded>0</occluded>
        <difficult>0</difficult>
        <bndbox>
            <xmin>888</xmin>
            <ymin>2153</ymin>
            <xmax>935</xmax>
            <ymax>2182</ymax>
        </bndbox>
    </object>
    <object>
        <name>inlinemf</name>
        <pose>Unspecified</pose>
        <truncated>0</truncated>
        <occluded>0</occluded>
        <difficult>0</difficult>
        <bndbox>
            <xmin>587</xmin>
            <ymin>1972</ymin>
            <xmax>764</xmax>
            <ymax>2002</ymax>
        </bndbox>
    </object>
    <object>
        <name>inlinemf</name>
        <pose>Unspecified</pose>
        <truncated>0</truncated>
        <occluded>0</occluded>
        <difficult>0</difficult>
        <bndbox>
            <xmin>1463</xmin>
            <ymin>1864</ymin>
            <xmax>1509</xmax>
            <ymax>1895</ymax>
        </bndbox>
    </object>
    <object>
        <name>inlinemf</name>
        <pose>Unspecified</pose>
        <truncated>0</truncated>
        <occluded>0</occluded>
        <difficult>0</difficult>
        <bndbox>
            <xmin>947</xmin>
            <ymin>2118</ymin>
            <xmax>993</xmax>
            <ymax>2146</ymax>
        </bndbox>
    </object>
    <object>
        <name>inlinemf</name>
        <pose>Unspecified</pose>
        <truncated>0</truncated>
        <occluded>0</occluded>
        <difficult>0</difficult>
        <bndbox>
            <xmin>174</xmin>
            <ymin>1503</ymin>
            <xmax>352</xmax>
            <ymax>1530</ymax>
        </bndbox>
    </object>
    <object>
        <name>inlinemf</name>
        <pose>Unspecified</pose>
        <truncated>0</truncated>
        <occluded>0</occluded>
        <difficult>0</difficult>
        <bndbox>
            <xmin>1033</xmin>
            <ymin>1720</ymin>
            <xmax>1054</xmax>
            <ymax>1743</ymax>
        </bndbox>
    </object>
    <object>
        <name>inlinemf</name>
        <pose>Unspecified</pose>
        <truncated>0</truncated>
        <occluded>0</occluded>
        <difficult>0</difficult>
        <bndbox>
            <xmin>1336</xmin>
            <ymin>1973</ymin>
            <xmax>1382</xmax>
            <ymax>2005</ymax>
        </bndbox>
    </object>
    <object>
        <name>inlinemf</name>
        <pose>Unspecified</pose>
        <truncated>0</truncated>
        <occluded>0</occluded>
        <difficult>0</difficult>
        <bndbox>
            <xmin>591</xmin>
            <ymin>1939</ymin>
            <xmax>622</xmax>
            <ymax>1962</ymax>
        </bndbox>
    </object>
    <object>
        <name>inlinemf</name>
        <pose>Unspecified</pose>
        <truncated>0</truncated>
        <occluded>0</occluded>
        <difficult>0</difficult>
        <bndbox>
            <xmin>1409</xmin>
            <ymin>1759</ymin>
            <xmax>1425</xmax>
            <ymax>1782</ymax>
        </bndbox>
    </object>
</annotation>