<annotation>
    <filename>177_006.png</filename>
    <size>
        <width>1481</width>
        <height>2073</height>
        <depth>3</depth>
    </size>
    <segmented>0</segmented>
    <object>
        <name>inlinemf</name>
        <pose>Unspecified</pose>
        <truncated>0</truncated>
        <occluded>0</occluded>
        <difficult>0</difficult>
        <bndbox>
            <xmin>384</xmin>
            <ymin>1062</ymin>
            <xmax>437</xmax>
            <ymax>1091</ymax>
        </bndbox>
    </object>
    <object>
        <name>inlinemf</name>
        <pose>Unspecified</pose>
        <truncated>0</truncated>
        <occluded>0</occluded>
        <difficult>0</difficult>
        <bndbox>
            <xmin>997</xmin>
            <ymin>1668</ymin>
            <xmax>1054</xmax>
            <ymax>1704</ymax>
        </bndbox>
    </object>
    <object>
        <name>inlinemf</name>
        <pose>Unspecified</pose>
        <truncated>0</truncated>
        <occluded>0</occluded>
        <difficult>0</difficult>
        <bndbox>
            <xmin>374</xmin>
            <ymin>1149</ymin>
            <xmax>474</xmax>
            <ymax>1180</ymax>
        </bndbox>
    </object>
    <object>
        <name>displaymf</name>
        <pose>Unspecified</pose>
        <truncated>0</truncated>
        <occluded>0</occluded>
        <difficult>0</difficult>
        <bndbox>
            <xmin>180</xmin>
            <ymin>205</ymin>
            <xmax>595</xmax>
            <ymax>1008</ymax>
        </bndbox>
    </object>
    <object>
        <name>inlinemf</name>
        <pose>Unspecified</pose>
        <truncated>0</truncated>
        <occluded>0</occluded>
        <difficult>0</difficult>
        <bndbox>
            <xmin>265</xmin>
            <ymin>1594</ymin>
            <xmax>295</xmax>
            <ymax>1614</ymax>
        </bndbox>
    </object>
    <object>
        <name>inlinemf</name>
        <pose>Unspecified</pose>
        <truncated>0</truncated>
        <occluded>0</occluded>
        <difficult>0</difficult>
        <bndbox>
            <xmin>509</xmin>
            <ymin>1635</ymin>
            <xmax>538</xmax>
            <ymax>1651</ymax>
        </bndbox>
    </object>
    <object>
        <name>inlinemf</name>
        <pose>Unspecified</pose>
        <truncated>0</truncated>
        <occluded>0</occluded>
        <difficult>0</difficult>
        <bndbox>
            <xmin>452</xmin>
            <ymin>1324</ymin>
            <xmax>511</xmax>
            <ymax>1351</ymax>
        </bndbox>
    </object>
    <object>
        <name>inlinemf</name>
        <pose>Unspecified</pose>
        <truncated>0</truncated>
        <occluded>0</occluded>
        <difficult>0</difficult>
        <bndbox>
            <xmin>267</xmin>
            <ymin>1193</ymin>
            <xmax>453</xmax>
            <ymax>1233</ymax>
        </bndbox>
    </object>
    <object>
        <name>inlinemf</name>
        <pose>Unspecified</pose>
        <truncated>0</truncated>
        <occluded>0</occluded>
        <difficult>0</difficult>
        <bndbox>
            <xmin>481</xmin>
            <ymin>1412</ymin>
            <xmax>538</xmax>
            <ymax>1439</ymax>
        </bndbox>
    </object>
    <object>
        <name>inlinemf</name>
        <pose>Unspecified</pose>
        <truncated>0</truncated>
        <occluded>0</occluded>
        <difficult>0</difficult>
        <bndbox>
            <xmin>456</xmin>
            <ymin>1843</ymin>
            <xmax>514</xmax>
            <ymax>1875</ymax>
        </bndbox>
    </object>
    <object>
        <name>inlinemf</name>
        <pose>Unspecified</pose>
        <truncated>0</truncated>
        <occluded>0</occluded>
        <difficult>0</difficult>
        <bndbox>
            <xmin>293</xmin>
            <ymin>1060</ymin>
            <xmax>347</xmax>
            <ymax>1092</ymax>
        </bndbox>
    </object>
    <object>
        <name>inlinemf</name>
        <pose>Unspecified</pose>
        <truncated>0</truncated>
        <occluded>0</occluded>
        <difficult>0</difficult>
        <bndbox>
            <xmin>639</xmin>
            <ymin>1196</ymin>
            <xmax>670</xmax>
            <ymax>1225</ymax>
        </bndbox>
    </object>
    <object>
        <name>inlinemf</name>
        <pose>Unspecified</pose>
        <truncated>0</truncated>
        <occluded>0</occluded>
        <difficult>0</difficult>
        <bndbox>
            <xmin>287</xmin>
            <ymin>1412</ymin>
            <xmax>342</xmax>
            <ymax>1438</ymax>
        </bndbox>
    </object>
    <object>
        <name>inlinemf</name>
        <pose>Unspecified</pose>
        <truncated>0</truncated>
        <occluded>0</occluded>
        <difficult>0</difficult>
        <bndbox>
            <xmin>178</xmin>
            <ymin>1282</ymin>
            <xmax>303</xmax>
            <ymax>1310</ymax>
        </bndbox>
    </object>
    <object>
        <name>inlinemf</name>
        <pose>Unspecified</pose>
        <truncated>0</truncated>
        <occluded>0</occluded>
        <difficult>0</difficult>
        <bndbox>
            <xmin>432</xmin>
            <ymin>1238</ymin>
            <xmax>710</xmax>
            <ymax>1269</ymax>
        </bndbox>
    </object>
    <object>
        <name>inlinemf</name>
        <pose>Unspecified</pose>
        <truncated>0</truncated>
        <occluded>0</occluded>
        <difficult>0</difficult>
        <bndbox>
            <xmin>362</xmin>
            <ymin>1455</ymin>
            <xmax>383</xmax>
            <ymax>1482</ymax>
        </bndbox>
    </object>
</annotation>