<annotation>
    <filename>235_000.png</filename>
    <size>
        <width>1653</width>
        <height>2339</height>
        <depth>3</depth>
    </size>
    <segmented>0</segmented>
    <object>
        <name>inlinemf</name>
        <pose>Unspecified</pose>
        <truncated>0</truncated>
        <occluded>0</occluded>
        <difficult>0</difficult>
        <bndbox>
            <xmin>1212</xmin>
            <ymin>1993</ymin>
            <xmax>1353</xmax>
            <ymax>2026</ymax>
        </bndbox>
    </object>
    <object>
        <name>inlinemf</name>
        <pose>Unspecified</pose>
        <truncated>0</truncated>
        <occluded>0</occluded>
        <difficult>0</difficult>
        <bndbox>
            <xmin>1290</xmin>
            <ymin>2032</ymin>
            <xmax>1409</xmax>
            <ymax>2062</ymax>
        </bndbox>
    </object>
    <object>
        <name>inlinemf</name>
        <pose>Unspecified</pose>
        <truncated>0</truncated>
        <occluded>0</occluded>
        <difficult>0</difficult>
        <bndbox>
            <xmin>1165</xmin>
            <ymin>2068</ymin>
            <xmax>1203</xmax>
            <ymax>2097</ymax>
        </bndbox>
    </object>
    <object>
        <name>inlinemf</name>
        <pose>Unspecified</pose>
        <truncated>0</truncated>
        <occluded>0</occluded>
        <difficult>0</difficult>
        <bndbox>
            <xmin>1270</xmin>
            <ymin>1923</ymin>
            <xmax>1306</xmax>
            <ymax>1951</ymax>
        </bndbox>
    </object>
    <object>
        <name>inlinemf</name>
        <pose>Unspecified</pose>
        <truncated>0</truncated>
        <occluded>0</occluded>
        <difficult>0</difficult>
        <bndbox>
            <xmin>1359</xmin>
            <ymin>2104</ymin>
            <xmax>1515</xmax>
            <ymax>2138</ymax>
        </bndbox>
    </object>
    <object>
        <name>inlinemf</name>
        <pose>Unspecified</pose>
        <truncated>0</truncated>
        <occluded>0</occluded>
        <difficult>0</difficult>
        <bndbox>
            <xmin>1035</xmin>
            <ymin>2068</ymin>
            <xmax>1080</xmax>
            <ymax>2097</ymax>
        </bndbox>
    </object>
    <object>
        <name>inlinemf</name>
        <pose>Unspecified</pose>
        <truncated>0</truncated>
        <occluded>0</occluded>
        <difficult>0</difficult>
        <bndbox>
            <xmin>1466</xmin>
            <ymin>1923</ymin>
            <xmax>1515</xmax>
            <ymax>1952</ymax>
        </bndbox>
    </object>
    <object>
        <name>inlinemf</name>
        <pose>Unspecified</pose>
        <truncated>0</truncated>
        <occluded>0</occluded>
        <difficult>0</difficult>
        <bndbox>
            <xmin>1033</xmin>
            <ymin>2106</ymin>
            <xmax>1191</xmax>
            <ymax>2138</ymax>
        </bndbox>
    </object>
    <object>
        <name>inlinemf</name>
        <pose>Unspecified</pose>
        <truncated>0</truncated>
        <occluded>0</occluded>
        <difficult>0</difficult>
        <bndbox>
            <xmin>1144</xmin>
            <ymin>1921</ymin>
            <xmax>1182</xmax>
            <ymax>1953</ymax>
        </bndbox>
    </object>
</annotation>