<annotation>
    <filename>266_003.png</filename>
    <size>
        <width>1653</width>
        <height>2339</height>
        <depth>3</depth>
    </size>
    <segmented>0</segmented>
    <object>
        <name>displaymf</name>
        <pose>Unspecified</pose>
        <truncated>0</truncated>
        <occluded>0</occluded>
        <difficult>0</difficult>
        <bndbox>
            <xmin>196</xmin>
            <ymin>490</ymin>
            <xmax>654</xmax>
            <ymax>558</ymax>
        </bndbox>
    </object>
    <object>
        <name>inlinemf</name>
        <pose>Unspecified</pose>
        <truncated>0</truncated>
        <occluded>0</occluded>
        <difficult>0</difficult>
        <bndbox>
            <xmin>861</xmin>
            <ymin>1738</ymin>
            <xmax>1269</xmax>
            <ymax>1793</ymax>
        </bndbox>
    </object>
    <object>
        <name>displaymf</name>
        <pose>Unspecified</pose>
        <truncated>0</truncated>
        <occluded>0</occluded>
        <difficult>0</difficult>
        <bndbox>
            <xmin>199</xmin>
            <ymin>1859</ymin>
            <xmax>724</xmax>
            <ymax>2007</ymax>
        </bndbox>
    </object>
    <object>
        <name>inlinemf</name>
        <pose>Unspecified</pose>
        <truncated>0</truncated>
        <occluded>0</occluded>
        <difficult>0</difficult>
        <bndbox>
            <xmin>698</xmin>
            <ymin>1352</ymin>
            <xmax>778</xmax>
            <ymax>1382</ymax>
        </bndbox>
    </object>
    <object>
        <name>inlinemf</name>
        <pose>Unspecified</pose>
        <truncated>0</truncated>
        <occluded>0</occluded>
        <difficult>0</difficult>
        <bndbox>
            <xmin>249</xmin>
            <ymin>1273</ymin>
            <xmax>301</xmax>
            <ymax>1309</ymax>
        </bndbox>
    </object>
    <object>
        <name>inlinemf</name>
        <pose>Unspecified</pose>
        <truncated>0</truncated>
        <occluded>0</occluded>
        <difficult>0</difficult>
        <bndbox>
            <xmin>335</xmin>
            <ymin>1273</ymin>
            <xmax>398</xmax>
            <ymax>1307</ymax>
        </bndbox>
    </object>
    <object>
        <name>inlinemf</name>
        <pose>Unspecified</pose>
        <truncated>0</truncated>
        <occluded>0</occluded>
        <difficult>0</difficult>
        <bndbox>
            <xmin>593</xmin>
            <ymin>406</ymin>
            <xmax>611</xmax>
            <ymax>432</ymax>
        </bndbox>
    </object>
    <object>
        <name>inlinemf</name>
        <pose>Unspecified</pose>
        <truncated>0</truncated>
        <occluded>0</occluded>
        <difficult>0</difficult>
        <bndbox>
            <xmin>1025</xmin>
            <ymin>1901</ymin>
            <xmax>1195</xmax>
            <ymax>1943</ymax>
        </bndbox>
    </object>
    <object>
        <name>displaymf</name>
        <pose>Unspecified</pose>
        <truncated>0</truncated>
        <occluded>0</occluded>
        <difficult>0</difficult>
        <bndbox>
            <xmin>906</xmin>
            <ymin>2032</ymin>
            <xmax>1342</xmax>
            <ymax>2113</ymax>
        </bndbox>
    </object>
    <object>
        <name>displaymf</name>
        <pose>Unspecified</pose>
        <truncated>0</truncated>
        <occluded>0</occluded>
        <difficult>0</difficult>
        <bndbox>
            <xmin>198</xmin>
            <ymin>1210</ymin>
            <xmax>489</xmax>
            <ymax>1254</ymax>
        </bndbox>
    </object>
    <object>
        <name>inlinemf</name>
        <pose>Unspecified</pose>
        <truncated>0</truncated>
        <occluded>0</occluded>
        <difficult>0</difficult>
        <bndbox>
            <xmin>702</xmin>
            <ymin>1390</ymin>
            <xmax>780</xmax>
            <ymax>1427</ymax>
        </bndbox>
    </object>
    <object>
        <name>inlinemf</name>
        <pose>Unspecified</pose>
        <truncated>0</truncated>
        <occluded>0</occluded>
        <difficult>0</difficult>
        <bndbox>
            <xmin>1144</xmin>
            <ymin>1195</ymin>
            <xmax>1165</xmax>
            <ymax>1220</ymax>
        </bndbox>
    </object>
    <object>
        <name>inlinemf</name>
        <pose>Unspecified</pose>
        <truncated>0</truncated>
        <occluded>0</occluded>
        <difficult>0</difficult>
        <bndbox>
            <xmin>524</xmin>
            <ymin>1278</ymin>
            <xmax>546</xmax>
            <ymax>1304</ymax>
        </bndbox>
    </object>
    <object>
        <name>inlinemf</name>
        <pose>Unspecified</pose>
        <truncated>0</truncated>
        <occluded>0</occluded>
        <difficult>0</difficult>
        <bndbox>
            <xmin>150</xmin>
            <ymin>1392</ymin>
            <xmax>226</xmax>
            <ymax>1425</ymax>
        </bndbox>
    </object>
    <object>
        <name>inlinemf</name>
        <pose>Unspecified</pose>
        <truncated>0</truncated>
        <occluded>0</occluded>
        <difficult>0</difficult>
        <bndbox>
            <xmin>432</xmin>
            <ymin>608</ymin>
            <xmax>509</xmax>
            <ymax>639</ymax>
        </bndbox>
    </object>
    <object>
        <name>inlinemf</name>
        <pose>Unspecified</pose>
        <truncated>0</truncated>
        <occluded>0</occluded>
        <difficult>0</difficult>
        <bndbox>
            <xmin>280</xmin>
            <ymin>1468</ymin>
            <xmax>393</xmax>
            <ymax>1510</ymax>
        </bndbox>
    </object>
    <object>
        <name>inlinemf</name>
        <pose>Unspecified</pose>
        <truncated>0</truncated>
        <occluded>0</occluded>
        <difficult>0</difficult>
        <bndbox>
            <xmin>1122</xmin>
            <ymin>1719</ymin>
            <xmax>1153</xmax>
            <ymax>1738</ymax>
        </bndbox>
    </object>
    <object>
        <name>displaymf</name>
        <pose>Unspecified</pose>
        <truncated>0</truncated>
        <occluded>0</occluded>
        <difficult>0</difficult>
        <bndbox>
            <xmin>903</xmin>
            <ymin>818</ymin>
            <xmax>1387</xmax>
            <ymax>1180</ymax>
        </bndbox>
    </object>
    <object>
        <name>inlinemf</name>
        <pose>Unspecified</pose>
        <truncated>0</truncated>
        <occluded>0</occluded>
        <difficult>0</difficult>
        <bndbox>
            <xmin>526</xmin>
            <ymin>1431</ymin>
            <xmax>716</xmax>
            <ymax>1472</ymax>
        </bndbox>
    </object>
    <object>
        <name>inlinemf</name>
        <pose>Unspecified</pose>
        <truncated>0</truncated>
        <occluded>0</occluded>
        <difficult>0</difficult>
        <bndbox>
            <xmin>909</xmin>
            <ymin>1591</ymin>
            <xmax>969</xmax>
            <ymax>1623</ymax>
        </bndbox>
    </object>
    <object>
        <name>inlinemf</name>
        <pose>Unspecified</pose>
        <truncated>0</truncated>
        <occluded>0</occluded>
        <difficult>0</difficult>
        <bndbox>
            <xmin>1427</xmin>
            <ymin>1235</ymin>
            <xmax>1500</xmax>
            <ymax>1265</ymax>
        </bndbox>
    </object>
    <object>
        <name>inlinemf</name>
        <pose>Unspecified</pose>
        <truncated>0</truncated>
        <occluded>0</occluded>
        <difficult>0</difficult>
        <bndbox>
            <xmin>1214</xmin>
            <ymin>1592</ymin>
            <xmax>1296</xmax>
            <ymax>1627</ymax>
        </bndbox>
    </object>
    <object>
        <name>displaymf</name>
        <pose>Unspecified</pose>
        <truncated>0</truncated>
        <occluded>0</occluded>
        <difficult>0</difficult>
        <bndbox>
            <xmin>196</xmin>
            <ymin>1524</ymin>
            <xmax>692</xmax>
            <ymax>1753</ymax>
        </bndbox>
    </object>
    <object>
        <name>inlinemf</name>
        <pose>Unspecified</pose>
        <truncated>0</truncated>
        <occluded>0</occluded>
        <difficult>0</difficult>
        <bndbox>
            <xmin>883</xmin>
            <ymin>1720</ymin>
            <xmax>903</xmax>
            <ymax>1736</ymax>
        </bndbox>
    </object>
    <object>
        <name>inlinemf</name>
        <pose>Unspecified</pose>
        <truncated>0</truncated>
        <occluded>0</occluded>
        <difficult>0</difficult>
        <bndbox>
            <xmin>565</xmin>
            <ymin>1318</ymin>
            <xmax>643</xmax>
            <ymax>1351</ymax>
        </bndbox>
    </object>
    <object>
        <name>displaymf</name>
        <pose>Unspecified</pose>
        <truncated>0</truncated>
        <occluded>0</occluded>
        <difficult>0</difficult>
        <bndbox>
            <xmin>905</xmin>
            <ymin>1314</ymin>
            <xmax>1329</xmax>
            <ymax>1528</ymax>
        </bndbox>
    </object>
    <object>
        <name>inlinemf</name>
        <pose>Unspecified</pose>
        <truncated>0</truncated>
        <occluded>0</occluded>
        <difficult>0</difficult>
        <bndbox>
            <xmin>183</xmin>
            <ymin>1163</ymin>
            <xmax>207</xmax>
            <ymax>1189</ymax>
        </bndbox>
    </object>
    <object>
        <name>inlinemf</name>
        <pose>Unspecified</pose>
        <truncated>0</truncated>
        <occluded>0</occluded>
        <difficult>0</difficult>
        <bndbox>
            <xmin>1275</xmin>
            <ymin>1903</ymin>
            <xmax>1376</xmax>
            <ymax>1940</ymax>
        </bndbox>
    </object>
    <object>
        <name>inlinemf</name>
        <pose>Unspecified</pose>
        <truncated>0</truncated>
        <occluded>0</occluded>
        <difficult>0</difficult>
        <bndbox>
            <xmin>428</xmin>
            <ymin>967</ymin>
            <xmax>532</xmax>
            <ymax>996</ymax>
        </bndbox>
    </object>
    <object>
        <name>inlinemf</name>
        <pose>Unspecified</pose>
        <truncated>0</truncated>
        <occluded>0</occluded>
        <difficult>0</difficult>
        <bndbox>
            <xmin>543</xmin>
            <ymin>610</ymin>
            <xmax>619</xmax>
            <ymax>638</ymax>
        </bndbox>
    </object>
    <object>
        <name>inlinemf</name>
        <pose>Unspecified</pose>
        <truncated>0</truncated>
        <occluded>0</occluded>
        <difficult>0</difficult>
        <bndbox>
            <xmin>1418</xmin>
            <ymin>1705</ymin>
            <xmax>1500</xmax>
            <ymax>1738</ymax>
        </bndbox>
    </object>
    <object>
        <name>inlinemf</name>
        <pose>Unspecified</pose>
        <truncated>0</truncated>
        <occluded>0</occluded>
        <difficult>0</difficult>
        <bndbox>
            <xmin>217</xmin>
            <ymin>1116</ymin>
            <xmax>315</xmax>
            <ymax>1152</ymax>
        </bndbox>
    </object>
    <object>
        <name>inlinemf</name>
        <pose>Unspecified</pose>
        <truncated>0</truncated>
        <occluded>0</occluded>
        <difficult>0</difficult>
        <bndbox>
            <xmin>1347</xmin>
            <ymin>1791</ymin>
            <xmax>1365</xmax>
            <ymax>1816</ymax>
        </bndbox>
    </object>
    <object>
        <name>inlinemf</name>
        <pose>Unspecified</pose>
        <truncated>0</truncated>
        <occluded>0</occluded>
        <difficult>0</difficult>
        <bndbox>
            <xmin>858</xmin>
            <ymin>1822</ymin>
            <xmax>966</xmax>
            <ymax>1861</ymax>
        </bndbox>
    </object>
    <object>
        <name>inlinemf</name>
        <pose>Unspecified</pose>
        <truncated>0</truncated>
        <occluded>0</occluded>
        <difficult>0</difficult>
        <bndbox>
            <xmin>150</xmin>
            <ymin>2062</ymin>
            <xmax>345</xmax>
            <ymax>2101</ymax>
        </bndbox>
    </object>
    <object>
        <name>inlinemf</name>
        <pose>Unspecified</pose>
        <truncated>0</truncated>
        <occluded>0</occluded>
        <difficult>0</difficult>
        <bndbox>
            <xmin>299</xmin>
            <ymin>1354</ymin>
            <xmax>380</xmax>
            <ymax>1393</ymax>
        </bndbox>
    </object>
    <object>
        <name>inlinemf</name>
        <pose>Unspecified</pose>
        <truncated>0</truncated>
        <occluded>0</occluded>
        <difficult>0</difficult>
        <bndbox>
            <xmin>491</xmin>
            <ymin>1079</ymin>
            <xmax>581</xmax>
            <ymax>1114</ymax>
        </bndbox>
    </object>
    <object>
        <name>displaymf</name>
        <pose>Unspecified</pose>
        <truncated>0</truncated>
        <occluded>0</occluded>
        <difficult>0</difficult>
        <bndbox>
            <xmin>199</xmin>
            <ymin>216</ymin>
            <xmax>655</xmax>
            <ymax>391</ymax>
        </bndbox>
    </object>
    <object>
        <name>inlinemf</name>
        <pose>Unspecified</pose>
        <truncated>0</truncated>
        <occluded>0</occluded>
        <difficult>0</difficult>
        <bndbox>
            <xmin>151</xmin>
            <ymin>1431</ymin>
            <xmax>238</xmax>
            <ymax>1468</ymax>
        </bndbox>
    </object>
</annotation>