<annotation>
    <filename>284_001.png</filename>
    <size>
        <width>1653</width>
        <height>2339</height>
        <depth>3</depth>
    </size>
    <segmented>0</segmented>
    <object>
        <name>inlinemf</name>
        <pose>Unspecified</pose>
        <truncated>0</truncated>
        <occluded>0</occluded>
        <difficult>0</difficult>
        <bndbox>
            <xmin>573</xmin>
            <ymin>1793</ymin>
            <xmax>591</xmax>
            <ymax>1817</ymax>
        </bndbox>
    </object>
    <object>
        <name>inlinemf</name>
        <pose>Unspecified</pose>
        <truncated>0</truncated>
        <occluded>0</occluded>
        <difficult>0</difficult>
        <bndbox>
            <xmin>1046</xmin>
            <ymin>216</ymin>
            <xmax>1076</xmax>
            <ymax>242</ymax>
        </bndbox>
    </object>
    <object>
        <name>inlinemf</name>
        <pose>Unspecified</pose>
        <truncated>0</truncated>
        <occluded>0</occluded>
        <difficult>0</difficult>
        <bndbox>
            <xmin>154</xmin>
            <ymin>1748</ymin>
            <xmax>188</xmax>
            <ymax>1775</ymax>
        </bndbox>
    </object>
    <object>
        <name>inlinemf</name>
        <pose>Unspecified</pose>
        <truncated>0</truncated>
        <occluded>0</occluded>
        <difficult>0</difficult>
        <bndbox>
            <xmin>399</xmin>
            <ymin>1129</ymin>
            <xmax>427</xmax>
            <ymax>1155</ymax>
        </bndbox>
    </object>
    <object>
        <name>inlinemf</name>
        <pose>Unspecified</pose>
        <truncated>0</truncated>
        <occluded>0</occluded>
        <difficult>0</difficult>
        <bndbox>
            <xmin>538</xmin>
            <ymin>1047</ymin>
            <xmax>563</xmax>
            <ymax>1073</ymax>
        </bndbox>
    </object>
    <object>
        <name>inlinemf</name>
        <pose>Unspecified</pose>
        <truncated>0</truncated>
        <occluded>0</occluded>
        <difficult>0</difficult>
        <bndbox>
            <xmin>633</xmin>
            <ymin>1124</ymin>
            <xmax>667</xmax>
            <ymax>1154</ymax>
        </bndbox>
    </object>
    <object>
        <name>inlinemf</name>
        <pose>Unspecified</pose>
        <truncated>0</truncated>
        <occluded>0</occluded>
        <difficult>0</difficult>
        <bndbox>
            <xmin>349</xmin>
            <ymin>1706</ymin>
            <xmax>387</xmax>
            <ymax>1740</ymax>
        </bndbox>
    </object>
    <object>
        <name>inlinemf</name>
        <pose>Unspecified</pose>
        <truncated>0</truncated>
        <occluded>0</occluded>
        <difficult>0</difficult>
        <bndbox>
            <xmin>453</xmin>
            <ymin>1786</ymin>
            <xmax>474</xmax>
            <ymax>1813</ymax>
        </bndbox>
    </object>
    <object>
        <name>inlinemf</name>
        <pose>Unspecified</pose>
        <truncated>0</truncated>
        <occluded>0</occluded>
        <difficult>0</difficult>
        <bndbox>
            <xmin>1390</xmin>
            <ymin>728</ymin>
            <xmax>1441</xmax>
            <ymax>760</ymax>
        </bndbox>
    </object>
    <object>
        <name>inlinemf</name>
        <pose>Unspecified</pose>
        <truncated>0</truncated>
        <occluded>0</occluded>
        <difficult>0</difficult>
        <bndbox>
            <xmin>598</xmin>
            <ymin>1714</ymin>
            <xmax>618</xmax>
            <ymax>1739</ymax>
        </bndbox>
    </object>
    <object>
        <name>inlinemf</name>
        <pose>Unspecified</pose>
        <truncated>0</truncated>
        <occluded>0</occluded>
        <difficult>0</difficult>
        <bndbox>
            <xmin>682</xmin>
            <ymin>1787</ymin>
            <xmax>717</xmax>
            <ymax>1818</ymax>
        </bndbox>
    </object>
    <object>
        <name>inlinemf</name>
        <pose>Unspecified</pose>
        <truncated>0</truncated>
        <occluded>0</occluded>
        <difficult>0</difficult>
        <bndbox>
            <xmin>484</xmin>
            <ymin>1708</ymin>
            <xmax>503</xmax>
            <ymax>1733</ymax>
        </bndbox>
    </object>
    <object>
        <name>inlinemf</name>
        <pose>Unspecified</pose>
        <truncated>0</truncated>
        <occluded>0</occluded>
        <difficult>0</difficult>
        <bndbox>
            <xmin>1166</xmin>
            <ymin>413</ymin>
            <xmax>1210</xmax>
            <ymax>442</ymax>
        </bndbox>
    </object>
    <object>
        <name>inlinemf</name>
        <pose>Unspecified</pose>
        <truncated>0</truncated>
        <occluded>0</occluded>
        <difficult>0</difficult>
        <bndbox>
            <xmin>473</xmin>
            <ymin>1743</ymin>
            <xmax>512</xmax>
            <ymax>1778</ymax>
        </bndbox>
    </object>
    <object>
        <name>inlinemf</name>
        <pose>Unspecified</pose>
        <truncated>0</truncated>
        <occluded>0</occluded>
        <difficult>0</difficult>
        <bndbox>
            <xmin>450</xmin>
            <ymin>1165</ymin>
            <xmax>542</xmax>
            <ymax>1193</ymax>
        </bndbox>
    </object>
    <object>
        <name>inlinemf</name>
        <pose>Unspecified</pose>
        <truncated>0</truncated>
        <occluded>0</occluded>
        <difficult>0</difficult>
        <bndbox>
            <xmin>404</xmin>
            <ymin>1086</ymin>
            <xmax>451</xmax>
            <ymax>1119</ymax>
        </bndbox>
    </object>
    <object>
        <name>inlinemf</name>
        <pose>Unspecified</pose>
        <truncated>0</truncated>
        <occluded>0</occluded>
        <difficult>0</difficult>
        <bndbox>
            <xmin>1271</xmin>
            <ymin>451</ymin>
            <xmax>1322</xmax>
            <ymax>483</ymax>
        </bndbox>
    </object>
    <object>
        <name>inlinemf</name>
        <pose>Unspecified</pose>
        <truncated>0</truncated>
        <occluded>0</occluded>
        <difficult>0</difficult>
        <bndbox>
            <xmin>150</xmin>
            <ymin>1132</ymin>
            <xmax>191</xmax>
            <ymax>1155</ymax>
        </bndbox>
    </object>
    <object>
        <name>inlinemf</name>
        <pose>Unspecified</pose>
        <truncated>0</truncated>
        <occluded>0</occluded>
        <difficult>0</difficult>
        <bndbox>
            <xmin>237</xmin>
            <ymin>1706</ymin>
            <xmax>273</xmax>
            <ymax>1735</ymax>
        </bndbox>
    </object>
    <object>
        <name>inlinemf</name>
        <pose>Unspecified</pose>
        <truncated>0</truncated>
        <occluded>0</occluded>
        <difficult>0</difficult>
        <bndbox>
            <xmin>237</xmin>
            <ymin>1046</ymin>
            <xmax>264</xmax>
            <ymax>1071</ymax>
        </bndbox>
    </object>
    <object>
        <name>displaymf</name>
        <pose>Unspecified</pose>
        <truncated>0</truncated>
        <occluded>0</occluded>
        <difficult>0</difficult>
        <bndbox>
            <xmin>191</xmin>
            <ymin>1213</ymin>
            <xmax>791</xmax>
            <ymax>1690</ymax>
        </bndbox>
    </object>
    <object>
        <name>inlinemf</name>
        <pose>Unspecified</pose>
        <truncated>0</truncated>
        <occluded>0</occluded>
        <difficult>0</difficult>
        <bndbox>
            <xmin>256</xmin>
            <ymin>1794</ymin>
            <xmax>283</xmax>
            <ymax>1819</ymax>
        </bndbox>
    </object>
    <object>
        <name>inlinemf</name>
        <pose>Unspecified</pose>
        <truncated>0</truncated>
        <occluded>0</occluded>
        <difficult>0</difficult>
        <bndbox>
            <xmin>1231</xmin>
            <ymin>1085</ymin>
            <xmax>1283</xmax>
            <ymax>1113</ymax>
        </bndbox>
    </object>
    <object>
        <name>inlinemf</name>
        <pose>Unspecified</pose>
        <truncated>0</truncated>
        <occluded>0</occluded>
        <difficult>0</difficult>
        <bndbox>
            <xmin>544</xmin>
            <ymin>1746</ymin>
            <xmax>564</xmax>
            <ymax>1774</ymax>
        </bndbox>
    </object>
    <object>
        <name>inlinemf</name>
        <pose>Unspecified</pose>
        <truncated>0</truncated>
        <occluded>0</occluded>
        <difficult>0</difficult>
        <bndbox>
            <xmin>277</xmin>
            <ymin>741</ymin>
            <xmax>313</xmax>
            <ymax>775</ymax>
        </bndbox>
    </object>
    <object>
        <name>displaymf</name>
        <pose>Unspecified</pose>
        <truncated>0</truncated>
        <occluded>0</occluded>
        <difficult>0</difficult>
        <bndbox>
            <xmin>196</xmin>
            <ymin>881</ymin>
            <xmax>706</xmax>
            <ymax>1014</ymax>
        </bndbox>
    </object>
    <object>
        <name>inlinemf</name>
        <pose>Unspecified</pose>
        <truncated>0</truncated>
        <occluded>0</occluded>
        <difficult>0</difficult>
        <bndbox>
            <xmin>935</xmin>
            <ymin>223</ymin>
            <xmax>953</xmax>
            <ymax>247</ymax>
        </bndbox>
    </object>
    <object>
        <name>inlinemf</name>
        <pose>Unspecified</pose>
        <truncated>0</truncated>
        <occluded>0</occluded>
        <difficult>0</difficult>
        <bndbox>
            <xmin>1104</xmin>
            <ymin>1086</ymin>
            <xmax>1153</xmax>
            <ymax>1112</ymax>
        </bndbox>
    </object>
    <object>
        <name>inlinemf</name>
        <pose>Unspecified</pose>
        <truncated>0</truncated>
        <occluded>0</occluded>
        <difficult>0</difficult>
        <bndbox>
            <xmin>151</xmin>
            <ymin>1792</ymin>
            <xmax>179</xmax>
            <ymax>1815</ymax>
        </bndbox>
    </object>
    <object>
        <name>inlinemf</name>
        <pose>Unspecified</pose>
        <truncated>0</truncated>
        <occluded>0</occluded>
        <difficult>0</difficult>
        <bndbox>
            <xmin>752</xmin>
            <ymin>1045</ymin>
            <xmax>792</xmax>
            <ymax>1078</ymax>
        </bndbox>
    </object>
</annotation>